README.rst
setup.py
django_fast_test/__init__.py
django_fast_test.egg-info/PKG-INFO
django_fast_test.egg-info/SOURCES.txt
django_fast_test.egg-info/dependency_links.txt
django_fast_test.egg-info/requires.txt
django_fast_test.egg-info/top_level.txt
django_fast_test/management/__init__.py
django_fast_test/management/commands/__init__.py
django_fast_test/management/commands/fast_test.py